python_markdown_document_offsets_injection_extension/__init__.py
python_markdown_document_offsets_injection_extension/extension.py
python_markdown_document_offsets_injection_extension-0.5.16.dist-info/METADATA
python_markdown_document_offsets_injection_extension-0.5.16.dist-info/WHEEL
python_markdown_document_offsets_injection_extension-0.5.16.dist-info/entry_points.txt
python_markdown_document_offsets_injection_extension-0.5.16.dist-info/RECORD
