Metadata-Version: 2.4
Name: python_markdown_document_offsets_injection_extension
Version: 0.5.16
Summary: A Python-Markdown compiler plugin that put markdown words offset to the output HTML.
Author-email: HikariLan <hikarilan@minecraft.kim>
License: Apache-2.0
Requires-Python: >=3.8
Requires-Dist: markdown>=3.6
